estadistica_facil/Agrupacion.py
estadistica_facil/Frecuencias.py
estadistica_facil/IMedible.py
estadistica_facil/Intervalo.py
estadistica_facil/MedicionesAgrupacion.py
estadistica_facil/Muestra.py
estadistica_facil/__init__.py
estadistica_facil-1.0.18.dist-info/licenses/LICENSE
estadistica_facil-1.0.18.dist-info/WHEEL
estadistica_facil-1.0.18.dist-info/METADATA
estadistica_facil-1.0.18.dist-info/RECORD
