Metadata-Version: 2.4
Name: estadistica_facil
Version: 1.0.18
Summary: _Permite realizar operaciones estadisticas de manera sencilla_
Author-email: Benjamín Peralta <benjaminp158@gmail.com>
Classifier: License :: OSI Approved :: MIT License
License-File: LICENSE
Requires-Dist: numpy>=1.26.4
Project-URL: Home, https://github.com/PeraBaja/excel-python
